{
  "title": "The American scholar",
  "creator": [
    "Parker, Theodore, 1810-1860",
    "Cooke, George Willis, 1848-1923"
  ],
  "description": [
    "The American scholar.--Ralph Waldo Emerson.--William Ellery Channing.--Prescott as an historian.--Prescott's Conquest of Mexico.--Hildreth's United States.--Macaulay's History of England.--Buckle's History of civilization.--Henry Ward Beecher.--Life and character of Dr. Follen.--German literature",
    "\"Into this volume have been collected a number of Theodore Parker's more scholarly and critical essays.\"--Editor's pref"
  ],
  "publisher": "Boston : American Unitarian Association",
  "date": "1907",
  "language": "eng",
  "page-progression": "lr",
  "sponsor": "Boston Library Consortium Member Libraries",
  "contributor": "Wellesley College Library",
  "scanningcenter": "boston",
  "mediatype": "texts",
  "call_number": "b1734881x",
  "repub_state": "4",
  "updatedate": "2010-08-06 14:16:59",
  "updater": "TomK-loader",
  "identifier": "americanscholar00park",
  "uploader": "tom.k@archive.org",
  "addeddate": "2010-08-06 14:17:01",
  "publicdate": "2010-08-06 14:17:07",
  "ppi": "400",
  "camera": "Canon 5D",
  "operator": "scanner-manuel-dennis@archive.org",
  "scanner": "scribe8.boston.archive.org",
  "scandate": "20100818231302",
  "imagecount": "556",
  "foldoutcount": "0",
  "identifier-access": "http://www.archive.org/details/americanscholar00park",
  "identifier-ark": "ark:/13960/t8nc6q90p",
  "bookplateleaf": "0004",
  "ocr": "ABBYY FineReader 8.0",
  "curation": "[curator]andy-seronick@archive.org[/curator][date]20100820005716[/date][state]approved[/state]",
  "sponsordate": "20100831",
  "collection": [
    "Wellesley_College_Library",
    "blc",
    "americana"
  ],
  "backup_location": "ia903606_2",
  "external-identifier": "urn:oclc:record:690765544",
  "filesxml": "Wed Dec 23 4:03:50 UTC 2020",
  "ocr_module_version": "0.0.13",
  "ocr_converted": "abbyy-to-hocr 1.1.7",
  "page_number_confidence": "99",
  "lccn": "07039034 /REV",
  "associated-names": "Cooke, George Willis, 1848-1923",
  "page_number_module_version": "1.0.5"
}
