{
  "title": "American architecture",
  "creator": "Schuyler, Montgomery, 1843-1914",
  "subject": "Architecture",
  "description": "The point of view.--Concerning Queen Anne.--The Vanderbilt houses.--The Brooklyn Bridge as a monument.--An American cathedral.--Glimpses of western architecture: I. Chicago. II. St. Paul and Minneapolis",
  "publisher": "New York, Harper & Brothers",
  "date": "1892",
  "language": "eng",
  "page-progression": "lr",
  "sponsor": "Boston Library Consortium Member Libraries",
  "contributor": "Wellesley College Library",
  "scanningcenter": "boston",
  "mediatype": "texts",
  "collection": [
    "Wellesley_College_Library",
    "blc",
    "americana"
  ],
  "call_number": "b12116580",
  "updatedate": "2009-07-02 17:58:09",
  "updater": "tricia-gray@archive.org",
  "identifier": "americanarchitec92schu",
  "uploader": "tricia-gray@archive.org",
  "addeddate": "2009-07-02 17:58:12",
  "publicdate": "2009-07-02 17:58:16",
  "ppi": "400",
  "camera": "Canon 5D",
  "operator": "scanner-aaron-needle@archive.org",
  "scanner": "scribe7.boston.archive.org",
  "scandate": "20090713122240",
  "imagecount": "238",
  "foldoutcount": "0",
  "identifier-access": "http://www.archive.org/details/americanarchitec92schu",
  "identifier-ark": "ark:/13960/t8kd2c65t",
  "repub_state": "4",
  "curation": "[curator]melissa@archive.org[/curator][date]20091201161519[/date][state]approved[/state]",
  "sponsordate": "20090731",
  "backup_location": "ia903603_12",
  "external-identifier": "urn:oclc:record:1155998545",
  "filesxml": "Wed Dec 23 3:40:18 UTC 2020",
  "lccn": "11028649",
  "ocr_module_version": "0.0.21",
  "ocr_converted": "abbyy-to-hocr 1.1.37",
  "page_number_confidence": "83",
  "page_number_module_version": "1.0.3"
}
